king/__init__.py
king/alg/__init__.py
king/alg/basic_alg.py
king/alg/circle_alg.py
king/alg/conic_alg.py
king/alg/ellipse_alg.py
king/alg/hyperbola_alg.py
king/alg/parabola_alg.py
king/alg/plane_geometry_alg.py
king/alg/triangle_center_alg.py
king/alg/test/__init__.py
king/alg/test/test.py
king/alg/test/test02.py
king/core/__init__.py
king/core/king_animation.py
king/core/king_decorater.py
king/core/king_decorater_multi_geometry.py
king/core/king_figure.py
king/core/king_geometry.py
king/geometry/__init__.py
king/geometry/king_conic.py
king/geometry/king_conic_generator.py
king/geometry/king_conic_graph.py
king/geometry/king_conic_graph_generator.py
king/geometry/king_curve.py
king/geometry/king_empty_geometry.py
king/geometry/king_equation.py
king/geometry/king_function.py
king/geometry/king_parametric_equation.py
king/geometry/king_plane_geometry_graph.py
king/geometry/king_plane_geometry_graph_generator.py
king/geometry/king_point_on_curve.py
king/geometry/king_regular_polygon.py
king/geometry/king_slider.py
king/geometry/king_triangle_center_generator.py
king/geometry_attribute/__init__.py
king/geometry_attribute/affine.py
king/geometry_attribute/angle.py
king/geometry_attribute/distance.py
king_paint-1.5.dist-info/LICENSE
king_paint-1.5.dist-info/METADATA
king_paint-1.5.dist-info/WHEEL
king_paint-1.5.dist-info/top_level.txt
king_paint-1.5.dist-info/RECORD
